deopy/__init__.py
deopy/deopy.py
deopy-0.0.7.dist-info/LICENSE
deopy-0.0.7.dist-info/METADATA
deopy-0.0.7.dist-info/WHEEL
deopy-0.0.7.dist-info/top_level.txt
deopy-0.0.7.dist-info/RECORD
