Metadata-Version: 2.1
Name: deopy
Version: 0.0.7
Summary: A python library that helps you de-obfuscate/decrypt obfuscated python code
Home-page: https://github.com/painor/deopy
Author: painor
Author-email: pi.oussama@gmail.com
License: UNKNOWN
Platform: UNKNOWN
Classifier: Programming Language :: Python :: 3
Classifier: License :: OSI Approved :: MIT License
Classifier: Operating System :: OS Independent
Requires-Python: >=3.6
Requires-Dist: requests
Requires-Dist: uncompyle6
